clipyard/__init__.py
clipyard/cli.py
clipyard/downloader.py
clipyard/metadata.py
clipyard/models.py
clipyard/parsers.py
clipyard/py.typed
clipyard/url_utils.py
clipyard-0.2.0.dist-info/METADATA
clipyard-0.2.0.dist-info/WHEEL
clipyard-0.2.0.dist-info/entry_points.txt
clipyard-0.2.0.dist-info/RECORD
