Metadata-Version: 2.4
Name: clipyard
Version: 0.2.0
Summary: A lightweight tool with good defaults for downloading large video datasets.
Author-email: Rahul Somani <rsomani95@gmail.com>
Requires-Python: >=3.13
Requires-Dist: pandas>=2.3
Requires-Dist: tqdm>=4.67
Requires-Dist: yt-dlp>=2025.11.12
Provides-Extra: datasets
Requires-Dist: datasets>=4.4; extra == 'datasets'
Provides-Extra: dev
Requires-Dist: pytest>=9.0; extra == 'dev'
